pertvi/__init__.py
pertvi/model/__init__.py
pertvi/model/linearprob.py
pertvi/model/pertvi.py
pertvi/module/__init__.py
pertvi/module/pertvi.py
scshift/__init__.py
scshift-0.1.0.dist-info/LICENSE
scshift-0.1.0.dist-info/METADATA
scshift-0.1.0.dist-info/WHEEL
scshift-0.1.0.dist-info/top_level.txt
scshift-0.1.0.dist-info/RECORD
